benchmark.cpython-311-x86_64-linux-gnu.so
plant_care.cpython-311-x86_64-linux-gnu.so
wyr/__init__.py
wyr/atom.c
wyr/atom.cpython-311-x86_64-linux-gnu.so
wyr/atom_diff.c
wyr/atom_diff.cpython-311-x86_64-linux-gnu.so
wyr/benchmark_runner.c
wyr/benchmark_runner.cpython-311-x86_64-linux-gnu.so
wyr/benchmark_runner_helpers.c
wyr/benchmark_runner_helpers.cpython-311-x86_64-linux-gnu.so
wyr/cli.c
wyr/cli.cpython-311-x86_64-linux-gnu.so
wyr/code_utils.c
wyr/code_utils.cpython-311-x86_64-linux-gnu.so
wyr/configuration.c
wyr/configuration.cpython-311-x86_64-linux-gnu.so
wyr/log.c
wyr/log.cpython-311-x86_64-linux-gnu.so
wyr/metadata_extractor.c
wyr/metadata_extractor.cpython-311-x86_64-linux-gnu.so
wyr/synthetic_data_generator.c
wyr/synthetic_data_generator.cpython-311-x86_64-linux-gnu.so
wyr/template_extractor.c
wyr/template_extractor.cpython-311-x86_64-linux-gnu.so
wyr/trainer.c
wyr/trainer.cpython-311-x86_64-linux-gnu.so
wyr/atom_detectors/base.c
wyr/atom_detectors/base.cpython-311-x86_64-linux-gnu.so
wyr/atom_detectors/ollama_detector.c
wyr/atom_detectors/ollama_detector.cpython-311-x86_64-linux-gnu.so
wyr/atom_detectors/simple_detector.c
wyr/atom_detectors/simple_detector.cpython-311-x86_64-linux-gnu.so
wyr/commands/analyze_semantics.c
wyr/commands/analyze_semantics.cpython-311-x86_64-linux-gnu.so
wyr/commands/analyze_semantics_click.c
wyr/commands/analyze_semantics_click.cpython-311-x86_64-linux-gnu.so
wyr/commands/base_command.c
wyr/commands/base_command.cpython-311-x86_64-linux-gnu.so
wyr/commands/benchmark.c
wyr/commands/benchmark.cpython-311-x86_64-linux-gnu.so
wyr/commands/benchmark_click.c
wyr/commands/benchmark_click.cpython-311-x86_64-linux-gnu.so
wyr/commands/criticize.c
wyr/commands/criticize.cpython-311-x86_64-linux-gnu.so
wyr/commands/criticize_click.c
wyr/commands/criticize_click.cpython-311-x86_64-linux-gnu.so
wyr/commands/data.c
wyr/commands/data.cpython-311-x86_64-linux-gnu.so
wyr/commands/data_click.c
rewyr-0.1.2.dist-info/METADATA
rewyr-0.1.2.dist-info/WHEEL
rewyr-0.1.2.dist-info/entry_points.txt
rewyr-0.1.2.dist-info/top_level.txt
rewyr-0.1.2.dist-info/RECORD
