Metadata-Version: 2.4
Name: rewyr
Version: 0.1.2
Summary: A static analysis tool for detecting LLM integration in a codebase
Author: Zahy Bnaya
License: Proprietary
Classifier: Programming Language :: Python :: 3
Classifier: Operating System :: OS Independent
Classifier: License :: Other/Proprietary License
Requires-Python: >=3.8
Requires-Dist: pyyaml>=6.0
Requires-Dist: llm>=0.12.0
Requires-Dist: llm-groq>=0.8
Requires-Dist: python-dotenv>=1.0.0
Requires-Dist: jinja2>=3.1.2
Requires-Dist: click>=8.0.0
Requires-Dist: coloredlogs>=15.0.0
Requires-Dist: tabulate>=0.9.0
Provides-Extra: dev
Requires-Dist: pytest>=7.0.0; extra == "dev"
Requires-Dist: pytest-mock>=3.10.0; extra == "dev"
Requires-Dist: pytest-cov>=4.0.0; extra == "dev"
Requires-Dist: black>=23.0.0; extra == "dev"
Requires-Dist: isort>=5.12.0; extra == "dev"
Requires-Dist: flake8>=6.0.0; extra == "dev"
Requires-Dist: mypy>=1.8.0; extra == "dev"
Requires-Dist: pre-commit>=4.0.0; extra == "dev"
Provides-Extra: finetuning
Requires-Dist: transformers>=4.30.0; extra == "finetuning"
Requires-Dist: peft>=0.4.0; extra == "finetuning"
Requires-Dist: torch>=2.0.0; extra == "finetuning"
Requires-Dist: accelerate>=0.20.0; extra == "finetuning"
